gtfs_proto/__init__.py
gtfs_proto/__main__.py
gtfs_proto/base.py
gtfs_proto/delta.py
gtfs_proto/dmerge.py
gtfs_proto/gtfs_pb2.py
gtfs_proto/info.py
gtfs_proto/pack.py
gtfs_proto/util.py
gtfs_proto/wrapper.py
gtfs_proto/packers/__init__.py
gtfs_proto/packers/base.py
gtfs_proto/packers/calendar.py
gtfs_proto/packers/packers.py
gtfs_proto/packers/routes.py
gtfs_proto/packers/shapes.py
gtfs_proto/packers/stops.py
gtfs_proto/packers/transfers.py
gtfs_proto/packers/trips.py
gtfs_proto-0.1.0.dist-info/LICENSE
gtfs_proto-0.1.0.dist-info/METADATA
gtfs_proto-0.1.0.dist-info/WHEEL
gtfs_proto-0.1.0.dist-info/entry_points.txt
gtfs_proto-0.1.0.dist-info/top_level.txt
gtfs_proto-0.1.0.dist-info/RECORD
