Metadata-Version: 2.1
Name: gtfs-proto
Version: 0.1.0
Summary: Library to package and process GTFS feeds in a protobuf format
Author-email: Ilya Zverev <ilya@zverev.info>
License: Copyright (c) 2021, Ilya Zverev
Project-URL: Homepage, https://github.com/Zverik/gtfs_proto
Project-URL: Bug Tracker, https://github.com/Zverik/gtfs_proto/issues
Keywords: gtfs,transit,feed,gtp,command line
Classifier: Programming Language :: Python :: 3
Classifier: Development Status :: 3 - Alpha
Classifier: Intended Audience :: Developers
Classifier: License :: OSI Approved :: ISC License (ISCL)
Classifier: Operating System :: OS Independent
Classifier: Topic :: Software Development :: Libraries :: Python Modules
Classifier: Topic :: File Formats
Classifier: Topic :: Utilities
Requires-Python: >=3.9
License-File: LICENSE
Requires-Dist: zstandard
Requires-Dist: protobuf
